<xf:itemset xmlns:xf="http://www.w3.org/2002/xforms">
    <xf:item>
        <xf:label>addAutoIncrement</xf:label>
        <xf:value>addAutoIncrement</xf:value>
    </xf:item>
    <xf:item>
        <xf:label>addColumn</xf:label>
        <xf:value>addColumn</xf:value>
    </xf:item>
    <xf:item>
        <xf:label>addDefaultValue</xf:label>
        <xf:value>addDefaultValue</xf:value>
    </xf:item>
    <xf:item>
        <xf:label>addForeignKeyConstraint</xf:label>
        <xf:value>addForeignKeyConstraint</xf:value>
    </xf:item>
    <xf:item>
        <xf:label>addLookupTable</xf:label>
        <xf:value>addLookupTable</xf:value>
    </xf:item>
    <xf:item>
        <xf:label>addNotNullConstraint</xf:label>
        <xf:value>addNotNullConstraint</xf:value>
    </xf:item>
    <xf:item>
        <xf:label>addPrimaryKey</xf:label>
        <xf:value>addPrimaryKey</xf:value>
    </xf:item>
    <xf:item>
        <xf:label>alterSequence</xf:label>
        <xf:value>alterSequence</xf:value>
    </xf:item>
    <xf:item>
        <xf:label>createIndex</xf:label>
        <xf:value>createIndex</xf:value>
    </xf:item>
    <xf:item>
        <xf:label>createProcedure</xf:label>
        <xf:value>createProcedure</xf:value>
    </xf:item>
    <xf:item>
        <xf:label>createSequence</xf:label>
        <xf:value>createSequence</xf:value>
    </xf:item>
    <xf:item>
        <xf:label>createTable</xf:label>
        <xf:value>createTable</xf:value>
    </xf:item>
    <xf:item>
        <xf:label>createView</xf:label>
        <xf:value>createView</xf:value>
    </xf:item>
    <xf:item>
        <xf:label>customChange</xf:label>
        <xf:value>customChange</xf:value>
    </xf:item>
    <xf:item>
        <xf:label>delete</xf:label>
        <xf:value>delete</xf:value>
    </xf:item>
    <xf:item>
        <xf:label>dropAllForeignKeyConstraint</xf:label>
        <xf:value>dropAllForeignKeyConstraint</xf:value>
    </xf:item>
    <xf:item>
        <xf:label>dropColumn</xf:label>
        <xf:value>dropColumn</xf:value>
    </xf:item>
    <xf:item>
        <xf:label>dropDefaultValue</xf:label>
        <xf:value>dropDefaultValue</xf:value>
    </xf:item>
    <xf:item>
        <xf:label>dropForeignKeyConstraint</xf:label>
        <xf:value>dropForeignKeyConstraint</xf:value>
    </xf:item>
    <xf:item>
        <xf:label>dropIndex</xf:label>
        <xf:value>dropIndex</xf:value>
    </xf:item>
    <xf:item>
        <xf:label>dropNotNullConstraint</xf:label>
        <xf:value>dropNotNullConstraint</xf:value>
    </xf:item>
    <xf:item>
        <xf:label>dropPrimaryKey</xf:label>
        <xf:value>dropPrimaryKey</xf:value>
    </xf:item>
    <xf:item>
        <xf:label>dropSequence</xf:label>
        <xf:value>dropSequence</xf:value>
    </xf:item>
    <xf:item>
        <xf:label>dropTable</xf:label>
        <xf:value>dropTable</xf:value>
    </xf:item>
    <xf:item>
        <xf:label>dropUniqueConstraint</xf:label>
        <xf:value>dropUniqueConstraint</xf:value>
    </xf:item>
    <xf:item>
        <xf:label>dropView</xf:label>
        <xf:value>dropView</xf:value>
    </xf:item>
    <xf:item>
        <xf:label>empty</xf:label>
        <xf:value>empty</xf:value>
    </xf:item>
    <xf:item>
        <xf:label>executeCommand</xf:label>
        <xf:value>executeCommand</xf:value>
    </xf:item>
    <xf:item>
        <xf:label>insert</xf:label>
        <xf:value>insert</xf:value>
    </xf:item>
    <xf:item>
        <xf:label>loadData</xf:label>
        <xf:value>loadData</xf:value>
    </xf:item>
    <xf:item>
        <xf:label>loadUpdateData</xf:label>
        <xf:value>loadUpdateData</xf:value>
    </xf:item>
    <xf:item>
        <xf:label>mergeColumns</xf:label>
        <xf:value>mergeColumns</xf:value>
    </xf:item>
    <xf:item>
        <xf:label>modifyDataType</xf:label>
        <xf:value>modifyDataType</xf:value>
    </xf:item>
    <xf:item>
        <xf:label>renameColumn</xf:label>
        <xf:value>renameColumn</xf:value>
    </xf:item>
    <xf:item>
        <xf:label>renameTable</xf:label>
        <xf:value>renameTable</xf:value>
    </xf:item>
    <xf:item>
        <xf:label>renameView</xf:label>
        <xf:value>renameView</xf:value>
    </xf:item>
    <xf:item>
        <xf:label>sql</xf:label>
        <xf:value>sql</xf:value>
    </xf:item>
    <xf:item>
        <xf:label>sqlFile</xf:label>
        <xf:value>sqlFile</xf:value>
    </xf:item>
    <xf:item>
        <xf:label>stop</xf:label>
        <xf:value>stop</xf:value>
    </xf:item>
    <xf:item>
        <xf:label>tagDatabase</xf:label>
        <xf:value>tagDatabase</xf:value>
    </xf:item>
    <xf:item>
        <xf:label>update</xf:label>
        <xf:value>update</xf:value>
    </xf:item>
</xf:itemset>
